optim3d/__init__.py
optim3d/main.py
optim3d/utils.py
optim3d/config/reconstruct.json
optim3d/config/reconstruct_.json
optim3d-0.4.1.dist-info/COPYING
optim3d-0.4.1.dist-info/LICENSE
optim3d-0.4.1.dist-info/METADATA
optim3d-0.4.1.dist-info/WHEEL
optim3d-0.4.1.dist-info/entry_points.txt
optim3d-0.4.1.dist-info/top_level.txt
optim3d-0.4.1.dist-info/RECORD
