Metadata-Version: 2.2
Name: optim3d
Version: 0.4.1
Summary: CLI application for efficient and optimized reconstruction of large-scale 3D building models.
Home-page: https://github.com/Yarroudh/Optim3D
Author: Anass Yarroudh
Author-email: ayarroudh@uliege.be
License: BSD 3-Clause BSD 3-Clause "New" or "Revised" License
Requires-Python: >=3.9
License-File: LICENSE
License-File: COPYING
Requires-Dist: geopandas>=1.0.1
Requires-Dist: click>=8.1.8
Requires-Dist: osmnx>=2.0.1
Requires-Dist: rich>=13.9.4
Requires-Dist: psutil
Dynamic: author
Dynamic: author-email
Dynamic: description
Dynamic: description-content-type
Dynamic: home-page
Dynamic: license
Dynamic: requires-dist
Dynamic: requires-python
Dynamic: summary
